setup.cfg
setup.py
rapid/__init__.py
rapid/main.py
rapid.egg-info/PKG-INFO
rapid.egg-info/SOURCES.txt
rapid.egg-info/dependency_links.txt
rapid.egg-info/entry_points.txt
rapid.egg-info/top_level.txt
rapid/boilerplate/c
rapid/boilerplate/csharp
rapid/boilerplate/html
rapid/boilerplate/java
rapid/boilerplate/c/code.bp
rapid/boilerplate/cpp/code.bp
rapid/boilerplate/csharp/code.bp
rapid/boilerplate/empty/code.bp
rapid/boilerplate/html/code.bp
rapid/boilerplate/java/code.bp
rapid/boilerplate/python/code.bp