Metadata-Version: 1.0
Name: rapid
Version: 0.0.3
Summary: rapid generates boilerplate code through command line
Home-page: https://github.com/keshav11/rapid
Author: Keshav Gupta
Author-email: keshav@keshav.xyz
License: MIT
Download-URL: https://github.com/keshav11/rapid/tarball/0.0.3
Keywords: boilerplate,cli,generatecommand line
Platform: UNKNOWN
